tkinterwidgets/__init__.py
tkinterwidgets-0.0.3.dist-info/LICENSE.txt
tkinterwidgets-0.0.3.dist-info/METADATA
tkinterwidgets-0.0.3.dist-info/WHEEL
tkinterwidgets-0.0.3.dist-info/top_level.txt
tkinterwidgets-0.0.3.dist-info/RECORD
