Metadata-Version: 2.1
Name: tkinterwidgets
Version: 0.0.3
Summary: Tkinter Custom Widgets
Home-page: https://github.com/AST07/tkinterwidgets
Author: Aditya Singh Tejas
Author-email: adityasinghtejas03@gmail.com
License: MIT
Platform: UNKNOWN
Classifier: Programming Language :: Python :: 3
Classifier: License :: OSI Approved :: MIT License
Classifier: Operating System :: OS Independent
Requires-Python: >=3.0
